django_pg_migration_tools/__init__.py
django_pg_migration_tools/indexes.py
django_pg_migration_tools/operations.py
django_pg_migration_tools/py.typed
django_pg_migration_tools/timeouts.py
django_pg_migration_tools/management/__init__.py
django_pg_migration_tools/management/commands/__init__.py
django_pg_migration_tools/management/commands/migrate_with_timeouts.py
django_pg_migration_tools-0.1.24.dist-info/licenses/LICENSE
django_pg_migration_tools-0.1.24.dist-info/METADATA
django_pg_migration_tools-0.1.24.dist-info/WHEEL
django_pg_migration_tools-0.1.24.dist-info/top_level.txt
django_pg_migration_tools-0.1.24.dist-info/RECORD
