Metadata-Version: 2.4
Name: django_pg_migration_tools
Version: 0.1.24
Summary: Tools for making Django migrations safer and more scalable.
License: BSD 3-Clause License
Project-URL: repository, https://github.com/kraken-tech/django-pg-migration-tools
Project-URL: changelog, https://github.com/kraken-tech/django-pg-migration-tools/blob/main/CHANGELOG.md
Project-URL: docs, https://django-pg-migration-tools.readthedocs.io/
Classifier: Development Status :: 3 - Alpha
Classifier: Intended Audience :: Developers
Classifier: License :: OSI Approved :: BSD License
Classifier: Operating System :: OS Independent
Classifier: Programming Language :: Python :: 3 :: Only
Classifier: Programming Language :: Python :: 3
Classifier: Programming Language :: Python :: 3.10
Classifier: Programming Language :: Python :: 3.11
Classifier: Programming Language :: Python :: 3.12
Classifier: Typing :: Typed
Requires-Python: >=3.10
License-File: LICENSE
Provides-Extra: pytest-in-nox-base
Requires-Dist: coverage>=7.6.1; extra == "pytest-in-nox-base"
Requires-Dist: dj-database-url>=2.1.0; extra == "pytest-in-nox-base"
Requires-Dist: django-stubs>=5.0.0; extra == "pytest-in-nox-base"
Requires-Dist: environs>=11.0.0; extra == "pytest-in-nox-base"
Requires-Dist: nox>=2024.4.15; extra == "pytest-in-nox-base"
Requires-Dist: pytest-django>=4.8.0; extra == "pytest-in-nox-base"
Requires-Dist: pytest>=8.2.0; extra == "pytest-in-nox-base"
Provides-Extra: pytest-in-nox-psycopg3
Requires-Dist: django_pg_migration_tools[pytest-in-nox-base]; extra == "pytest-in-nox-psycopg3"
Requires-Dist: psycopg[binary]>=3.1.18; extra == "pytest-in-nox-psycopg3"
Provides-Extra: pytest-in-nox-psycopg2
Requires-Dist: django_pg_migration_tools[pytest-in-nox-base]; extra == "pytest-in-nox-psycopg2"
Requires-Dist: psycopg2-binary>=2.9.9; extra == "pytest-in-nox-psycopg2"
Provides-Extra: docs
Requires-Dist: sphinx>=7.4.7; extra == "docs"
Requires-Dist: sphinx_rtd_theme>=2.0.0; extra == "docs"
Requires-Dist: sphinx_lint>=0.9.1; extra == "docs"
Requires-Dist: sphinx_design>=0.6.1; extra == "docs"
Provides-Extra: dev
Requires-Dist: django_pg_migration_tools[pytest-in-nox-psycopg3]; extra == "dev"
Requires-Dist: django_pg_migration_tools[docs]; extra == "dev"
Requires-Dist: django>=4.2.0; extra == "dev"
Requires-Dist: ruff>=0.5.2; extra == "dev"
Requires-Dist: mypy>=1.10.1; extra == "dev"
Requires-Dist: pre-commit>=3.7.1; extra == "dev"
Requires-Dist: types-psycopg2>=2.9.21.20241019; extra == "dev"
Requires-Dist: build>=1.2.1; extra == "dev"
Requires-Dist: bump-my-version>=1.1.2; extra == "dev"
Dynamic: license-file
